Workbook

Sheet Cover
A1: DCF Valuation Model
A2: Educational sample | Shared DCF case | Unit: JPY million
B4: Model status
B5: Calculation integrity | C5: =Checks!B10 -> OK
B6: Decision readiness | C6: =Checks!B11 -> Educational sample / source review required
B8: Valuation convention | C8: Period-end convention: each forecast year-end / 1–5 periods
B10: Use caution | C10: Inputs are an educational case, not live market data. Review sources and assumptions before any real transaction use.

Sheet Inputs
A1: Inputs
A2: Blue cells are editable. Forecasts and valuation inputs come from the shared DCF educational case.
A4: Operating forecast | B4: FY2026 | C4: FY2027 | D4: FY2028 | E4: FY2029 | F4: FY2030
A5: Revenue | B5: 1100 | C5: 1200 | D5: 1320 | E5: 1452 | F5: 1597.2
A6: EBIT | B6: 120 | C6: 140 | D6: 160 | E6: 180 | F6: 200
A7: Tax Rate | B7: 0.3 | C7: 0.3 | D7: 0.3 | E7: 0.3 | F7: 0.3
A8: D&A | B8: 30 | C8: 32 | D8: 34 | E8: 36 | F8: 38
A9: Capex | B9: 30 | C9: 32 | D9: 34 | E9: 36 | F9: 38
A10: Increase in NWC | B10: 7.2 | C10: 6.9 | D10: 7.9 | E10: 9.5 | F10: 7.7
A13: Valuation and bridge inputs | B13: Value
A14: Risk-free Rate | B14: 0.015
A15: Equity Risk Premium | B15: 0.06
A16: Beta | B16: 1.1
A17: Pre-tax Cost of Debt | B17: 0.025
A18: Tax Rate | B18: 0.3
A19: Equity Weight | B19: 0.75
A20: Debt Weight | B20: 0.25
A21: Terminal Growth | B21: 0.015
A22: Cash | B22: 100
A23: Debt | B23: 350
A24: Debt-like Items | B24: 20
A25: Non-controlling Interests | B25: 10

Sheet Assumptions
A1: Assumptions
A2: Formula-driven WACC and valuation convention. WACC must exceed terminal growth.
A4: Assumption / calculation | B4: Value | C4: Definition / review
A5: Valuation convention | B5: Period-end convention | C5: Each forecast year-end / 1–5 periods
A8: Cost of Equity | B8: =Inputs!B14+Inputs!B16*Inputs!B15 -> 0.081 | C8: Risk-free Rate + Beta × Equity Risk Premium
A9: After-tax Cost of Debt | B9: =Inputs!B17*(1-Inputs!B18) -> 0.0175 | C9: Pre-tax Cost of Debt × (1 − Tax Rate)
A10: Capital Weights Sum | B10: =Inputs!B19+Inputs!B20 -> 1 | C10: Must equal 100.0%
A11: WACC | B11: =Inputs!B19*B8+Inputs!B20*B9 -> 0.065125 | C11: Equity Weight × CoE + Debt Weight × After-tax CoD
A12: Terminal Growth | B12: =Inputs!B21 -> 0.015 | C12: WACC > g required

Sheet PL
A1: PL
A2: Forecast operating results linked to Inputs. Unit: JPY million.
A4: Metric | B4: FY2026 | C4: FY2027 | D4: FY2028 | E4: FY2029 | F4: FY2030
A5: Revenue | B5: =Inputs!B5 -> 1100 | C5: =Inputs!C5 -> 1200 | D5: =Inputs!D5 -> 1320 | E5: =Inputs!E5 -> 1452 | F5: =Inputs!F5 -> 1597.2
A6: EBIT | B6: =Inputs!B6 -> 120 | C6: =Inputs!C6 -> 140 | D6: =Inputs!D6 -> 160 | E6: =Inputs!E6 -> 180 | F6: =Inputs!F6 -> 200
A7: Tax Rate | B7: =Inputs!B7 -> 0.3 | C7: =Inputs!C7 -> 0.3 | D7: =Inputs!D7 -> 0.3 | E7: =Inputs!E7 -> 0.3 | F7: =Inputs!F7 -> 0.3
A8: Tax on EBIT | B8: =-B6*B7 -> -36 | C8: =-C6*C7 -> -42 | D8: =-D6*D7 -> -48 | E8: =-E6*E7 -> -54 | F8: =-F6*F7 -> -60
A9: NOPAT | B9: =B6+B8 -> 84 | C9: =C6+C8 -> 98 | D9: =D6+D8 -> 112 | E9: =E6+E8 -> 126 | F9: =F6+F8 -> 140

Sheet BS
A1: BS
A2: Valuation-date balance sheet references and forecast working-capital movement. Unit: JPY million.
A4: Valuation-date bridge item | B4: Amount | C4: Treatment
A5: Cash | B5: =Inputs!B22 -> 100 | C5: Add to EV
A6: Debt | B6: =Inputs!B23 -> 350 | C6: Deduct from EV
A7: Debt-like Items | B7: =Inputs!B24 -> 20 | C7: Deduct from EV
A8: Non-controlling Interests | B8: =Inputs!B25 -> 10 | C8: Deduct from EV
A11: Increase in NWC | B11: FY2026 | C11: FY2027 | D11: FY2028 | E11: FY2029 | F11: FY2030
B12: =Inputs!B10 -> 7.2 | C12: =Inputs!C10 -> 6.9 | D12: =Inputs!D10 -> 7.9 | E12: =Inputs!E10 -> 9.5 | F12: =Inputs!F10 -> 7.7

Sheet CF
A1: CF
A2: FCFF is calculated from EBIT after tax, D&A, Capex and Increase in NWC. Unit: JPY million.
A4: Metric | B4: FY2026 | C4: FY2027 | D4: FY2028 | E4: FY2029 | F4: FY2030
A5: EBIT | B5: =PL!B6 -> 120 | C5: =PL!C6 -> 140 | D5: =PL!D6 -> 160 | E5: =PL!E6 -> 180 | F5: =PL!F6 -> 200
A6: Tax Rate | B6: =Inputs!B7 -> 0.3 | C6: =Inputs!C7 -> 0.3 | D6: =Inputs!D7 -> 0.3 | E6: =Inputs!E7 -> 0.3 | F6: =Inputs!F7 -> 0.3
A7: NOPAT | B7: =B5*(1-B6) -> 84 | C7: =C5*(1-C6) -> 98 | D7: =D5*(1-D6) -> 112 | E7: =E5*(1-E6) -> 126 | F7: =F5*(1-F6) -> 140
A8: D&A | B8: =Inputs!B8 -> 30 | C8: =Inputs!C8 -> 32 | D8: =Inputs!D8 -> 34 | E8: =Inputs!E8 -> 36 | F8: =Inputs!F8 -> 38
A9: Capex | B9: =Inputs!B9 -> 30 | C9: =Inputs!C9 -> 32 | D9: =Inputs!D9 -> 34 | E9: =Inputs!E9 -> 36 | F9: =Inputs!F9 -> 38
A10: Increase in NWC | B10: =Inputs!B10 -> 7.2 | C10: =Inputs!C10 -> 6.9 | D10: =Inputs!D10 -> 7.9 | E10: =Inputs!E10 -> 9.5 | F10: =Inputs!F10 -> 7.7
A11: FCFF | B11: =B5*(1-B6)+B8-B9-B10 -> 76.8 | C11: =C5*(1-C6)+C8-C9-C10 -> 91.1 | D11: =D5*(1-D6)+D8-D9-D10 -> 104.1 | E11: =E5*(1-E6)+E8-E9-E10 -> 116.5 | F11: =F5*(1-F6)+F8-F9-F10 -> 132.3

Sheet Schedules
A1: Schedules
A2: Operating schedules and period-end discount factors. Unit: JPY million unless stated.
A4: Schedule | B4: FY2026 | C4: FY2027 | D4: FY2028 | E4: FY2029 | F4: FY2030
A5: D&A | B5: =Inputs!B8 -> 30 | C5: =Inputs!C8 -> 32 | D5: =Inputs!D8 -> 34 | E5: =Inputs!E8 -> 36 | F5: =Inputs!F8 -> 38
A6: Capex | B6: =Inputs!B9 -> 30 | C6: =Inputs!C9 -> 32 | D6: =Inputs!D9 -> 34 | E6: =Inputs!E9 -> 36 | F6: =Inputs!F9 -> 38
A7: Increase in NWC | B7: =Inputs!B10 -> 7.2 | C7: =Inputs!C10 -> 6.9 | D7: =Inputs!D10 -> 7.9 | E7: =Inputs!E10 -> 9.5 | F7: =Inputs!F10 -> 7.7
A9: Discount Period | B9: 1 | C9: 2 | D9: 3 | E9: 4 | F9: 5
A10: Discount Factor | B10: =1/(1+Assumptions!$B$11)^B9 -> 0.93885694 | C10: =1/(1+Assumptions!$B$11)^C9 -> 0.88145236 | D10: =1/(1+Assumptions!$B$11)^D9 -> 0.82755766 | E10: =1/(1+Assumptions!$B$11)^E9 -> 0.77695826 | F10: =1/(1+Assumptions!$B$11)^F9 -> 0.72945265

Sheet DCF
A1: DCF
A2: Period-end DCF valuation, EV-to-Equity bridge and 5×5 WACC–growth sensitivity. Unit: JPY million.
A4: Valuation | B4: FY2026 | C4: FY2027 | D4: FY2028 | E4: FY2029 | F4: FY2030
A5: FCFF | B5: =CF!B11 -> 76.8 | C5: =CF!C11 -> 91.1 | D5: =CF!D11 -> 104.1 | E5: =CF!E11 -> 116.5 | F5: =CF!F11 -> 132.3
A6: Discount Factor | B6: =Schedules!B10 -> 0.93885694 | C6: =Schedules!C10 -> 0.88145236 | D6: =Schedules!D10 -> 0.82755766 | E6: =Schedules!E10 -> 0.77695826 | F6: =Schedules!F10 -> 0.72945265
A7: PV of FCFF | B7: =B5*B6 -> 72.104213 | C7: =C5*C6 -> 80.30031 | D7: =D5*D6 -> 86.148753 | E7: =E5*E6 -> 90.515637 | F7: =F5*F6 -> 96.506586
A10: PV of Explicit FCFF | B10: =SUM(B7:F7) -> 425.5755
A11: FCFF (n+1) | B11: =F5*(1+Assumptions!$B$12) -> 134.2845
A12: Terminal Value | B12: =IF(Assumptions!$B$11<=Assumptions!$B$12,NA(),B11/(Assumptions!$B$11-Assumptions!$B$12)) -> 2678.9925
A13: PV of Terminal Value | B13: =B12*F6 -> 1954.1982
A14: Enterprise Value | B14: =B10+B13 -> 2379.7737
A16: Cash | B16: =Inputs!B22 -> 100
A17: Debt | B17: =Inputs!B23 -> 350
A18: Debt-like Items | B18: =Inputs!B24 -> 20
A19: Non-controlling Interests | B19: =Inputs!B25 -> 10
A20: Equity Value | B20: =B14+B16-B17-B18-B19 -> 2099.7737
A24: Enterprise Value Sensitivity
B25: WACC / g | C25: 0.005 | D25: 0.01 | E25: 0.015 | F25: 0.02 | G25: 0.025
B26: 0.055 | C26: =IF($B26<=C$25,NA(),$B$5/(1+$B26)^1+$C$5/(1+$B26)^2+$D$5/(1+$B26)^3+$E$5/(1+$B26)^4+$F$5/(1+$B26)^5+($F$5*(1+C$25)/($B26-C$25))/(1+$B26)^5) -> 2473.2345 | D26: =IF($B26<=D$25,NA(),$B$5/(1+$B26)^1+$C$5/(1+$B26)^2+$D$5/(1+$B26)^3+$E$5/(1+$B26)^4+$F$5/(1+$B26)^5+($F$5*(1+D$25)/($B26-D$25))/(1+$B26)^5) -> 2710.5562 | E26: =IF($B26<=E$25,NA(),$B$5/(1+$B26)^1+$C$5/(1+$B26)^2+$D$5/(1+$B26)^3+$E$5/(1+$B26)^4+$F$5/(1+$B26)^5+($F$5*(1+E$25)/($B26-E$25))/(1+$B26)^5) -> 3007.2083 | F26: =IF($B26<=F$25,NA(),$B$5/(1+$B26)^1+$C$5/(1+$B26)^2+$D$5/(1+$B26)^3+$E$5/(1+$B26)^4+$F$5/(1+$B26)^5+($F$5*(1+F$25)/($B26-F$25))/(1+$B26)^5) -> 3388.6182 | G26: =IF($B26<=G$25,NA(),$B$5/(1+$B26)^1+$C$5/(1+$B26)^2+$D$5/(1+$B26)^3+$E$5/(1+$B26)^4+$F$5/(1+$B26)^5+($F$5*(1+G$25)/($B26-G$25))/(1+$B26)^5) -> 3897.1648
B27: 0.06 | C27: =IF($B27<=C$25,NA(),$B$5/(1+$B27)^1+$C$5/(1+$B27)^2+$D$5/(1+$B27)^3+$E$5/(1+$B27)^4+$F$5/(1+$B27)^5+($F$5*(1+C$25)/($B27-C$25))/(1+$B27)^5) -> 2238.5601 | D27: =IF($B27<=D$25,NA(),$B$5/(1+$B27)^1+$C$5/(1+$B27)^2+$D$5/(1+$B27)^3+$E$5/(1+$B27)^4+$F$5/(1+$B27)^5+($F$5*(1+D$25)/($B27-D$25))/(1+$B27)^5) -> 2429.0946 | E27: =IF($B27<=E$25,NA(),$B$5/(1+$B27)^1+$C$5/(1+$B27)^2+$D$5/(1+$B27)^3+$E$5/(1+$B27)^4+$F$5/(1+$B27)^5+($F$5*(1+E$25)/($B27-E$25))/(1+$B27)^5) -> 2661.9702 | F27: =IF($B27<=F$25,NA(),$B$5/(1+$B27)^1+$C$5/(1+$B27)^2+$D$5/(1+$B27)^3+$E$5/(1+$B27)^4+$F$5/(1+$B27)^5+($F$5*(1+F$25)/($B27-F$25))/(1+$B27)^5) -> 2953.0646 | G27: =IF($B27<=G$25,NA(),$B$5/(1+$B27)^1+$C$5/(1+$B27)^2+$D$5/(1+$B27)^3+$E$5/(1+$B27)^4+$F$5/(1+$B27)^5+($F$5*(1+G$25)/($B27-G$25))/(1+$B27)^5) -> 3327.3288
B28: 0.065 | C28: =IF($B28<=C$25,NA(),$B$5/(1+$B28)^1+$C$5/(1+$B28)^2+$D$5/(1+$B28)^3+$E$5/(1+$B28)^4+$F$5/(1+$B28)^5+($F$5*(1+C$25)/($B28-C$25))/(1+$B28)^5) -> 2043.1665 | D28: =IF($B28<=D$25,NA(),$B$5/(1+$B28)^1+$C$5/(1+$B28)^2+$D$5/(1+$B28)^3+$E$5/(1+$B28)^4+$F$5/(1+$B28)^5+($F$5*(1+D$25)/($B28-D$25))/(1+$B28)^5) -> 2198.9844 | E28: =IF($B28<=E$25,NA(),$B$5/(1+$B28)^1+$C$5/(1+$B28)^2+$D$5/(1+$B28)^3+$E$5/(1+$B28)^4+$F$5/(1+$B28)^5+($F$5*(1+E$25)/($B28-E$25))/(1+$B28)^5) -> 2385.966 | F28: =IF($B28<=F$25,NA(),$B$5/(1+$B28)^1+$C$5/(1+$B28)^2+$D$5/(1+$B28)^3+$E$5/(1+$B28)^4+$F$5/(1+$B28)^5+($F$5*(1+F$25)/($B28-F$25))/(1+$B28)^5) -> 2614.499 | G28: =IF($B28<=G$25,NA(),$B$5/(1+$B28)^1+$C$5/(1+$B28)^2+$D$5/(1+$B28)^3+$E$5/(1+$B28)^4+$F$5/(1+$B28)^5+($F$5*(1+G$25)/($B28-G$25))/(1+$B28)^5) -> 2900.1652
B29: 0.07 | C29: =IF($B29<=C$25,NA(),$B$5/(1+$B29)^1+$C$5/(1+$B29)^2+$D$5/(1+$B29)^3+$E$5/(1+$B29)^4+$F$5/(1+$B29)^5+($F$5*(1+C$25)/($B29-C$25))/(1+$B29)^5) -> 1877.985 | D29: =IF($B29<=D$25,NA(),$B$5/(1+$B29)^1+$C$5/(1+$B29)^2+$D$5/(1+$B29)^3+$E$5/(1+$B29)^4+$F$5/(1+$B29)^5+($F$5*(1+D$25)/($B29-D$25))/(1+$B29)^5) -> 2007.3838 | E29: =IF($B29<=E$25,NA(),$B$5/(1+$B29)^1+$C$5/(1+$B29)^2+$D$5/(1+$B29)^3+$E$5/(1+$B29)^4+$F$5/(1+$B29)^5+($F$5*(1+E$25)/($B29-E$25))/(1+$B29)^5) -> 2160.3096 | F29: =IF($B29<=F$25,NA(),$B$5/(1+$B29)^1+$C$5/(1+$B29)^2+$D$5/(1+$B29)^3+$E$5/(1+$B29)^4+$F$5/(1+$B29)^5+($F$5*(1+F$25)/($B29-F$25))/(1+$B29)^5) -> 2343.8206 | G29: =IF($B29<=G$25,NA(),$B$5/(1+$B29)^1+$C$5/(1+$B29)^2+$D$5/(1+$B29)^3+$E$5/(1+$B29)^4+$F$5/(1+$B29)^5+($F$5*(1+G$25)/($B29-G$25))/(1+$B29)^5) -> 2568.1118
B30: 0.075 | C30: =IF($B30<=C$25,NA(),$B$5/(1+$B30)^1+$C$5/(1+$B30)^2+$D$5/(1+$B30)^3+$E$5/(1+$B30)^4+$F$5/(1+$B30)^5+($F$5*(1+C$25)/($B30-C$25))/(1+$B30)^5) -> 1736.5383 | D30: =IF($B30<=D$25,NA(),$B$5/(1+$B30)^1+$C$5/(1+$B30)^2+$D$5/(1+$B30)^3+$E$5/(1+$B30)^4+$F$5/(1+$B30)^5+($F$5*(1+D$25)/($B30-D$25))/(1+$B30)^5) -> 1845.4024 | E30: =IF($B30<=E$25,NA(),$B$5/(1+$B30)^1+$C$5/(1+$B30)^2+$D$5/(1+$B30)^3+$E$5/(1+$B30)^4+$F$5/(1+$B30)^5+($F$5*(1+E$25)/($B30-E$25))/(1+$B30)^5) -> 1972.4105 | F30: =IF($B30<=F$25,NA(),$B$5/(1+$B30)^1+$C$5/(1+$B30)^2+$D$5/(1+$B30)^3+$E$5/(1+$B30)^4+$F$5/(1+$B30)^5+($F$5*(1+F$25)/($B30-F$25))/(1+$B30)^5) -> 2122.511 | G30: =IF($B30<=G$25,NA(),$B$5/(1+$B30)^1+$C$5/(1+$B30)^2+$D$5/(1+$B30)^3+$E$5/(1+$B30)^4+$F$5/(1+$B30)^5+($F$5*(1+G$25)/($B30-G$25))/(1+$B30)^5) -> 2302.6315

Sheet Checks
A1: Checks
A2: Formula-driven model checks. Calculation integrity is distinct from decision readiness.
A4: Check | B4: Formula result | C4: Status | D4: Purpose
A5: Capital weights sum | B5: =Inputs!B19+Inputs!B20 -> 1 | C5: =IF(ABS(B5-1)<0.000001,"OK","ERROR") -> OK | D5: Equity and debt weights must total 100%.
A6: WACC > Terminal Growth | B6: =Assumptions!B11>Assumptions!B12 -> TRUE | C6: =IF(B6,"OK","ERROR") -> OK | D6: Gordon Growth denominator must remain positive.
A7: EV bridge | B7: =DCF!B20-(DCF!B14+DCF!B16-DCF!B17-DCF!B18-DCF!B19) -> 0 | C7: =IF(ABS(B7)<0.000001,"OK","ERROR") -> OK | D7: Equity Value must reconcile to Enterprise Value adjustments.
A8: Formula-error count | B8: =SUMPRODUCT(--ISERROR(Assumptions!B8:B12))+SUMPRODUCT(--ISERROR(PL!B5:F9))+SUMPRODUCT(--ISERROR(BS!B5:F12))+SUMPRODUCT(--ISERROR(CF!B5:F11))+SUMPRODUCT(--ISERROR(Schedules!B5:F10))+SUMPRODUCT(--ISERROR(DCF!B5:G30)) -> 0 | C8: =IF(B8=0,"OK","ERROR") -> OK | D8: Counts formula errors in core calculation ranges.
A10: Calculation integrity | B10: =IF(COUNTIF(C5:C8,"<>OK")=0,"OK","ERROR") -> OK
A11: Decision readiness | B11: ="Educational sample / source review required" -> Educational sample / source review required
