Workbook

Sheet 使い方
A1: 類似会社選定ワークシート
A2: 類似上場会社の選定根拠を、一貫した手順で記録する教育用ワークブックです。
A4: 手順 | B4: 作業 | C4: 確認すること | D4: 出力
A5: 1 | B5: 対象会社の事業特性を確認 | C5: 対象会社の規模、収益性、製品・サービス構成を把握する | D5: 比較可能性の前提
A6: 2 | B6: 比較候補会社一覧を確認 | C6: 候補の情報源と基準日を記録し、母集団を広げる | D6: 候補12社
A7: 3 | B7: 比較会社選定表を採点 | C7: 12の評価軸を0〜3点で採点し、重大基準の不一致を確認する | D7: 総合スコア
A8: 4 | B8: 比較上の位置づけを分類 | C8: 各候補を比較上の位置づけに分類し、根拠と追加調査事項を残す | D8: 主要比較会社候補
A9: 5 | B9: 検討記録とチェックを確認 | C9: 位置づけ別の一覧、除外理由、未入力項目、データ欠損をレビューする | D9: レビュー記録
A11: 比較上の位置づけの定義
A12: 主要比較会社 | B12: 主要比較会社として扱う根拠を記録します
A13: 補完比較会社 | B13: 補完比較会社として扱う根拠を記録します
A14: 目標比較会社 | B14: 目標比較会社として扱う根拠を記録します
A15: 非比較会社 | B15: 非比較会社として扱う根拠を記録します
A16: 類似するが除外した会社 | B16: 類似するが除外した会社として扱う根拠を記録します
A17: 純粋比較会社ではない会社 | B17: 純粋比較会社ではない会社として扱う根拠を記録します

Sheet 対象会社の事業特性
A1: 対象会社の事業特性
A2: 比較対象の基準となる対象会社のプロファイル。青色セルは確認・更新対象です。
A3: 項目 | B3: 対象会社 | C3: 比較時の見方
A4: 売上高（百万円） | B4: 1100 | C4: 規模が近いか
A5: EBITDAマージン | B5: 0.164 | C5: 収益性が近いか
A6: 海外売上比率 | B6: 0.25 | C6: 地域・顧客構成が近いか
A7: 装置売上比率 | B7: 0.7 | C7: 製品とサービスの構成が近いか
A8: サービス売上比率 | B8: 0.3 | C8: 製品とサービスの構成が近いか
A9: 会社名 | B9: モデル製作株式会社 | C9: 対象会社の識別
A10: 事業内容 | B10: 製造業向け自動化装置・部品および保守サービス | C10: 収益モデルと製品ミックス
A11: 顧客市場 | B11: 国内外の電子部品・一般製造業 | C11: 顧客・最終市場の近さ
A12: 資本集約度 | B12: 中程度 | C12: 設備投資と固定費構造
A13: 循環性 | B13: 製造業設備投資に連動する中程度 | C13: 景気感応度と需要変動

Sheet 比較候補会社一覧
A1: 比較候補会社一覧
A2: 候補企業の母集団。情報源と基準日を明記し、除外前の観察を残します。
A3: ID | B3: 候補企業 | C3: 事業内容 | D3: 地域 | E3: 売上高（百万円） | F3: 成長率 | G3: EBITDAマージン | H3: サービス比率 | I3: 情報源 | J3: 基準日 | K3: 一次コメント
A4: takumi | B4: 匠オートメーション | C4: 自動化装置・保守 | D4: 日本 | E4: 1180 | F4: 0.07 | G4: 0.168 | H4: 0.28 | I4: 教育用ケースデータ | J4: 46222.625 | K4: 自動化装置と保守の事業構成が近く、売上規模、利益率、製造業顧客もケース企業と整合する。
A5: shinsei | B5: 新生精密システム | C5: 電子部品向け精密装置・保守 | D5: 日本 | E5: 980 | F5: 0.08 | G5: 0.159 | H5: 0.32 | I5: 教育用ケースデータ | J5: 46222.625 | K5: 電子部品向け装置と保守の構成が近く、顧客市場、利益率、資本集約度も比較可能な水準にある。
A6: tokai | B6: 東海ファクトリー機器 | C6: 工場向け生産設備 | D6: 日本 | E6: 1250 | F6: 0.05 | G6: 0.155 | H6: 0.24 | I6: 教育用ケースデータ | J6: 46222.625 | K6: 国内製造業向けの生産設備を主力とし、売上規模と資本集約度が近く、利益率も許容範囲にある。
A7: mirai | B7: 未来プロセス装置 | C7: 産業プロセス装置・部品 | D7: 日本 | E7: 1050 | F7: 0.09 | G7: 0.171 | H7: 0.22 | I7: 教育用ケースデータ | J7: 46222.625 | K7: 産業装置が主力で、売上規模、成長率、利益率が近い。顧客も設備投資を行う製造業で循環性が整合する。
A8: nippon | B8: 日本モーション技研 | C8: モーション制御装置・部品 | D8: 日本 | E8: 1320 | F8: 0.06 | G8: 0.162 | H8: 0.2 | I8: 教育用ケースデータ | J8: 46222.625 | K8: 装置・部品の売上ミックスと製造業顧客が近く、設備投資循環性、利益率、資本集約度も整合している。
A9: kyowa | B9: 協和製造ソリューション | C9: 製造ライン自動化装置 | D9: 日本 | E9: 1130 | F9: 0.06 | G9: 0.16 | H9: 0.26 | I9: 教育用ケースデータ | J9: 46222.625 | K9: 売上規模、顧客、地域がケース企業に近く、装置中心の事業構成と利益率も比較目的に適している。
A10: global | B10: グローバル産業ロボティクス | C10: 産業ロボット・自動化装置 | D10: グローバル | E10: 4800 | F10: 0.1 | G10: 0.195 | H10: 0.25 | I10: 教育用ケースデータ | J10: 46222.625 | K10: 自動化装置の事業と製造業顧客は近い一方、海外売上比率、規模、利益率が大きく異なり補完的な比較にとどめる。
A11: service | B11: サービスリンク工業 | C11: 産業装置保守・改修 | D11: 日本 | E11: 900 | F11: 0.11 | G11: 0.23 | H11: 0.68 | I11: 教育用ケースデータ | J11: 46222.625 | K11: 製造業顧客は近いが、保守比率と利益率が高く資本集約度も低い。サービス拡大後の将来像として参照する。
A12: heavy | B12: 大和重機械 | C12: 大型重機・建設機械 | D12: 日本 | E12: 2100 | F12: 0.03 | G12: 0.11 | H12: 0.18 | I12: 教育用ケースデータ | J12: 46222.625 | K12: 同じ機械分類でも大型受注と建設顧客が中心で、事業構成、資本集約度、循環性がケース企業と大きく異なる。
A13: close | B13: 中央FAテクノロジー | C13: FA装置・部品 | D13: 日本 | E13: 1080 | F13: 0.07 | G13: 該当なし | H13: 0.29 | I13: 教育用ケースデータ | J13: 46222.625 | K13: 事業構成、顧客、売上規模は非常に近いが、EBITDA情報が取得不能で利益率比較と倍率検証に使えない。
A14: group | B14: 統合エンジニアリングHD | C14: 複合エンジニアリング | D14: 日本・海外 | E14: 3600 | F14: 0.04 | G14: 0.135 | H14: 0.35 | I14: 教育用ケースデータ | J14: 46222.625 | K14: 対象に近い装置事業を含むが、複合企業で対象セグメントが小さい。事業構成、顧客、利益率を純粋に比較できない。
A15: turnaround | B15: 再生機工 | C15: 産業機械製造 | D15: 日本 | E15: 950 | F15: -0.04 | G15: 0.02 | H15: 0.15 | I15: 教育用ケースデータ | J15: 46222.625 | K15: 製造業顧客と産業機械の点は近いが、経営再建中で利益率、成長率、レバレッジが正常な比較水準にない。

Sheet 比較会社選定表
A1: 比較会社選定表
A2: 0〜3点で採点。重大基準の不一致、データ欠損、主要適格性ブロックを分けて記録します。
A3: ID | B3: 候補企業 | C3: 比較上の位置づけ | D3: 事業モデル | E3: 製品ミックス | F3: 顧客市場 | G3: 地域 | H3: 規模 | I3: 成長率 | J3: 利益率 | K3: 資本集約度 | L3: 循環性 | M3: レバレッジ | N3: 会計方針 | O3: 流動性 | P3: 総合スコア | Q3: 重大基準の不一致 | R3: データ欠損 | S3: 主要比較会社への採用不可 | T3: 位置づけ（元データ） | U3: 重大基準の低スコア | V3: コメント
A4: takumi | B4: 匠オートメーション | C4: 主要比較会社 | D4: 3 | E4: 3 | F4: 3 | G4: 3 | H4: 3 | I4: 3 | J4: 3 | K4: 3 | L4: 3 | M4: 2 | N4: 3 | O4: 2 | P4: =SUM(D4:O4) | Q4: FALSE | S4: FALSE | T4: 主要比較会社 | U4: =COUNTIF(D4:D4,"<2")+COUNTIF(E4:E4,"<2")+COUNTIF(F4:F4,"<2")+COUNTIF(K4:K4,"<2") | V4: 自動化装置と保守の事業構成が近く、売上規模、利益率、製造業顧客もケース企業と整合する。
A5: shinsei | B5: 新生精密システム | C5: 主要比較会社 | D5: 3 | E5: 3 | F5: 3 | G5: 3 | H5: 3 | I5: 3 | J5: 3 | K5: 3 | L5: 3 | M5: 2 | N5: 3 | O5: 2 | P5: =SUM(D5:O5) | Q5: FALSE | S5: FALSE | T5: 主要比較会社 | U5: =COUNTIF(D5:D5,"<2")+COUNTIF(E5:E5,"<2")+COUNTIF(F5:F5,"<2")+COUNTIF(K5:K5,"<2") | V5: 電子部品向け装置と保守の構成が近く、顧客市場、利益率、資本集約度も比較可能な水準にある。
A6: tokai | B6: 東海ファクトリー機器 | C6: 主要比較会社 | D6: 3 | E6: 2 | F6: 3 | G6: 3 | H6: 3 | I6: 2 | J6: 3 | K6: 3 | L6: 3 | M6: 2 | N6: 3 | O6: 2 | P6: =SUM(D6:O6) | Q6: FALSE | S6: FALSE | T6: 主要比較会社 | U6: =COUNTIF(D6:D6,"<2")+COUNTIF(E6:E6,"<2")+COUNTIF(F6:F6,"<2")+COUNTIF(K6:K6,"<2") | V6: 国内製造業向けの生産設備を主力とし、売上規模と資本集約度が近く、利益率も許容範囲にある。
A7: mirai | B7: 未来プロセス装置 | C7: 主要比較会社 | D7: 3 | E7: 2 | F7: 2 | G7: 3 | H7: 3 | I7: 3 | J7: 3 | K7: 3 | L7: 3 | M7: 2 | N7: 3 | O7: 2 | P7: =SUM(D7:O7) | Q7: FALSE | S7: FALSE | T7: 主要比較会社 | U7: =COUNTIF(D7:D7,"<2")+COUNTIF(E7:E7,"<2")+COUNTIF(F7:F7,"<2")+COUNTIF(K7:K7,"<2") | V7: 産業装置が主力で、売上規模、成長率、利益率が近い。顧客も設備投資を行う製造業で循環性が整合する。
A8: nippon | B8: 日本モーション技研 | C8: 主要比較会社 | D8: 3 | E8: 3 | F8: 3 | G8: 3 | H8: 2 | I8: 2 | J8: 3 | K8: 3 | L8: 3 | M8: 2 | N8: 3 | O8: 2 | P8: =SUM(D8:O8) | Q8: FALSE | S8: FALSE | T8: 主要比較会社 | U8: =COUNTIF(D8:D8,"<2")+COUNTIF(E8:E8,"<2")+COUNTIF(F8:F8,"<2")+COUNTIF(K8:K8,"<2") | V8: 装置・部品の売上ミックスと製造業顧客が近く、設備投資循環性、利益率、資本集約度も整合している。
A9: kyowa | B9: 協和製造ソリューション | C9: 主要比較会社 | D9: 3 | E9: 3 | F9: 3 | G9: 3 | H9: 3 | I9: 2 | J9: 3 | K9: 3 | L9: 3 | M9: 2 | N9: 3 | O9: 2 | P9: =SUM(D9:O9) | Q9: FALSE | S9: FALSE | T9: 主要比較会社 | U9: =COUNTIF(D9:D9,"<2")+COUNTIF(E9:E9,"<2")+COUNTIF(F9:F9,"<2")+COUNTIF(K9:K9,"<2") | V9: 売上規模、顧客、地域がケース企業に近く、装置中心の事業構成と利益率も比較目的に適している。
A10: global | B10: グローバル産業ロボティクス | C10: 補完比較会社 | D10: 3 | E10: 3 | F10: 3 | G10: 1 | H10: 0 | I10: 3 | J10: 1 | K10: 3 | L10: 3 | M10: 2 | N10: 2 | O10: 3 | P10: =SUM(D10:O10) | Q10: FALSE | S10: FALSE | T10: 補完比較会社 | U10: =COUNTIF(D10:D10,"<2")+COUNTIF(E10:E10,"<2")+COUNTIF(F10:F10,"<2")+COUNTIF(K10:K10,"<2") | V10: 自動化装置の事業と製造業顧客は近い一方、海外売上比率、規模、利益率が大きく異なり補完的な比較にとどめる。
A11: service | B11: サービスリンク工業 | C11: 目標比較会社 | D11: 2 | E11: 0 | F11: 3 | G11: 3 | H11: 2 | I11: 3 | J11: 0 | K11: 0 | L11: 2 | M11: 3 | N11: 3 | O11: 2 | P11: =SUM(D11:O11) | Q11: TRUE | S11: TRUE | T11: 目標比較会社 | U11: =COUNTIF(D11:D11,"<2")+COUNTIF(E11:E11,"<2")+COUNTIF(F11:F11,"<2")+COUNTIF(K11:K11,"<2") | V11: 製造業顧客は近いが、保守比率と利益率が高く資本集約度も低い。サービス拡大後の将来像として参照する。
A12: heavy | B12: 大和重機械 | C12: 非比較会社 | D12: 0 | E12: 1 | F12: 0 | G12: 3 | H12: 1 | I12: 1 | J12: 0 | K12: 0 | L12: 0 | M12: 1 | N12: 3 | O12: 2 | P12: =SUM(D12:O12) | Q12: TRUE | S12: TRUE | T12: 非比較会社 | U12: =COUNTIF(D12:D12,"<2")+COUNTIF(E12:E12,"<2")+COUNTIF(F12:F12,"<2")+COUNTIF(K12:K12,"<2") | V12: 同じ機械分類でも大型受注と建設顧客が中心で、事業構成、資本集約度、循環性がケース企業と大きく異なる。
A13: close | B13: 中央FAテクノロジー | C13: 類似するが除外した会社 | D13: 3 | E13: 3 | F13: 3 | G13: 3 | H13: 3 | I13: 3 | J13: 該当なし | K13: 3 | L13: 3 | M13: 2 | N13: 3 | O13: 該当なし | P13: =SUM(D13:O13) | Q13: FALSE | R13: margin, liquidity | S13: TRUE | T13: 類似するが除外した会社 | U13: =COUNTIF(D13:D13,"<2")+COUNTIF(E13:E13,"<2")+COUNTIF(F13:F13,"<2")+COUNTIF(K13:K13,"<2") | V13: 事業構成、顧客、売上規模は非常に近いが、EBITDA情報が取得不能で利益率比較と倍率検証に使えない。
A14: group | B14: 統合エンジニアリングHD | C14: 純粋比較会社ではない会社 | D14: 1 | E14: 1 | F14: 1 | G14: 1 | H14: 0 | I14: 1 | J14: 1 | K14: 1 | L14: 1 | M14: 1 | N14: 2 | O14: 2 | P14: =SUM(D14:O14) | Q14: TRUE | S14: TRUE | T14: 純粋比較会社ではない会社 | U14: =COUNTIF(D14:D14,"<2")+COUNTIF(E14:E14,"<2")+COUNTIF(F14:F14,"<2")+COUNTIF(K14:K14,"<2") | V14: 対象に近い装置事業を含むが、複合企業で対象セグメントが小さい。事業構成、顧客、利益率を純粋に比較できない。
A15: turnaround | B15: 再生機工 | C15: 純粋比較会社ではない会社 | D15: 2 | E15: 1 | F15: 2 | G15: 3 | H15: 2 | I15: 0 | J15: 0 | K15: 1 | L15: 2 | M15: 0 | N15: 2 | O15: 1 | P15: =SUM(D15:O15) | Q15: TRUE | S15: TRUE | T15: 純粋比較会社ではない会社 | U15: =COUNTIF(D15:D15,"<2")+COUNTIF(E15:E15,"<2")+COUNTIF(F15:F15,"<2")+COUNTIF(K15:K15,"<2") | V15: 製造業顧客と産業機械の点は近いが、経営再建中で利益率、成長率、レバレッジが正常な比較水準にない。

Sheet 比較上の位置づけ
A1: 比較上の位置づけ
A2: 位置づけと根拠に加え、重大不一致、データ欠損、主要比較会社への採用可否を独立して確認します。
A4: ID | B4: 候補企業 | C4: 比較上の位置づけ | D4: 採用・除外の根拠 | E4: 追加調査事項 | F4: データ利用可否 | G4: 重大基準の不一致 | H4: データ欠損 | I4: 主要比較会社への採用不可
A5: takumi | B5: 匠オートメーション | C5: 主要比較会社 | D5: 自動化装置と保守の事業構成が近く、売上規模、利益率、製造業顧客もケース企業と整合する。 | E5: なし | F5: 利用可 | G5: FALSE | I5: FALSE
A6: shinsei | B6: 新生精密システム | C6: 主要比較会社 | D6: 電子部品向け装置と保守の構成が近く、顧客市場、利益率、資本集約度も比較可能な水準にある。 | E6: なし | F6: 利用可 | G6: FALSE | I6: FALSE
A7: tokai | B7: 東海ファクトリー機器 | C7: 主要比較会社 | D7: 国内製造業向けの生産設備を主力とし、売上規模と資本集約度が近く、利益率も許容範囲にある。 | E7: なし | F7: 利用可 | G7: FALSE | I7: FALSE
A8: mirai | B8: 未来プロセス装置 | C8: 主要比較会社 | D8: 産業装置が主力で、売上規模、成長率、利益率が近い。顧客も設備投資を行う製造業で循環性が整合する。 | E8: なし | F8: 利用可 | G8: FALSE | I8: FALSE
A9: nippon | B9: 日本モーション技研 | C9: 主要比較会社 | D9: 装置・部品の売上ミックスと製造業顧客が近く、設備投資循環性、利益率、資本集約度も整合している。 | E9: なし | F9: 利用可 | G9: FALSE | I9: FALSE
A10: kyowa | B10: 協和製造ソリューション | C10: 主要比較会社 | D10: 売上規模、顧客、地域がケース企業に近く、装置中心の事業構成と利益率も比較目的に適している。 | E10: なし | F10: 利用可 | G10: FALSE | I10: FALSE
A11: global | B11: グローバル産業ロボティクス | C11: 補完比較会社 | D11: 自動化装置の事業と製造業顧客は近い一方、海外売上比率、規模、利益率が大きく異なり補完的な比較にとどめる。 | E11: なし | F11: 利用可 | G11: FALSE | I11: FALSE
A12: service | B12: サービスリンク工業 | C12: 目標比較会社 | D12: 製造業顧客は近いが、保守比率と利益率が高く資本集約度も低い。サービス拡大後の将来像として参照する。 | E12: なし | F12: 利用可 | G12: TRUE | I12: TRUE
A13: heavy | B13: 大和重機械 | C13: 非比較会社 | D13: 同じ機械分類でも大型受注と建設顧客が中心で、事業構成、資本集約度、循環性がケース企業と大きく異なる。 | E13: なし | F13: 利用可 | G13: TRUE | I13: TRUE
A14: close | B14: 中央FAテクノロジー | C14: 類似するが除外した会社 | D14: 事業構成、顧客、売上規模は非常に近いが、EBITDA情報が取得不能で利益率比較と倍率検証に使えない。 | E14: margin, liquidityの確認 | F14: 一部未確認 | G14: FALSE | H14: margin, liquidity | I14: TRUE
A15: group | B15: 統合エンジニアリングHD | C15: 純粋比較会社ではない会社 | D15: 対象に近い装置事業を含むが、複合企業で対象セグメントが小さい。事業構成、顧客、利益率を純粋に比較できない。 | E15: なし | F15: 利用可 | G15: TRUE | I15: TRUE
A16: turnaround | B16: 再生機工 | C16: 純粋比較会社ではない会社 | D16: 製造業顧客と産業機械の点は近いが、経営再建中で利益率、成長率、レバレッジが正常な比較水準にない。 | E16: なし | F16: 利用可 | G16: TRUE | I16: TRUE

Sheet 検討記録
A1: 検討記録
A2: 位置づけ別の候補一覧と、採用レンジ・除外理由をレビュー用に要約します。
A4: レビュー項目 | B4: 結果 | C4: 確認事項 | D4: メモ
A5: 主要比較会社数 | B5: =COUNTIF('比較上の位置づけ'!$C$5:$C$16,"主要比較会社") | C5: 中心レンジとして十分な数か
A6: 主要比較会社候補 | B6: =TEXTJOIN(", ",TRUE,IF('比較上の位置づけ'!$C$5:$C$16="主要比較会社",'比較上の位置づけ'!$B$5:$B$16,"")) | C6: 名称と位置づけを確認
A7: 補完比較会社候補 | B7: =TEXTJOIN(", ",TRUE,IF('比較上の位置づけ'!$C$5:$C$16="補完比較会社",'比較上の位置づけ'!$B$5:$B$16,"")) | C7: 補助的に参照する範囲
A8: 除外・非純粋比較会社 | B8: =TEXTJOIN(", ",TRUE,IF(('比較上の位置づけ'!$C$5:$C$16="類似するが除外した会社")+('比較上の位置づけ'!$C$5:$C$16="純粋比較会社ではない会社"),'比較上の位置づけ'!$B$5:$B$16,"")) | C8: 除外理由を説明可能にする
A9: データ未確認数 | B9: =COUNTIF('比較上の位置づけ'!$F$5:$F$16,"*未確認*") | C9: 必要な追加確認を実施
A10: レビュー結論 | B10: 主要比較会社を中心にレンジを検討。重大基準の不一致とデータ未確認を再確認する。 | C10: 最終採用レンジを別途記録

Sheet チェック
A1: チェック
A2: 入力漏れ、データ欠損、主要比較会社数、候補数を数式で確認します。
A3: チェック | B3: 結果 | C3: 判定基準
A4: 位置づけ未入力 | B4: =COUNTBLANK('比較上の位置づけ'!$C$5:$C$16) | C4: 0であること
A5: 理由未入力 | B5: =COUNTBLANK('比較上の位置づけ'!$D$5:$D$16) | C5: 0であること
A6: ID重複 | B6: =SUMPRODUCT((COUNTIF('比較上の位置づけ'!$A$5:$A$16,'比較上の位置づけ'!$A$5:$A$16)>1)*1) | C6: 0であること
A7: 主要比較会社・重大不一致 | B7: =COUNTIFS('比較上の位置づけ'!$C$5:$C$16,"主要比較会社",'比較上の位置づけ'!$G$5:$G$16,TRUE) | C7: 0であること
A8: 主要比較会社・データ欠損 | B8: =COUNTIFS('比較上の位置づけ'!$C$5:$C$16,"主要比較会社",'比較上の位置づけ'!$H$5:$H$16,"?*") | C8: 0であること
A9: 主要比較会社への採用不可 | B9: =COUNTIFS('比較上の位置づけ'!$C$5:$C$16,"主要比較会社",'比較上の位置づけ'!$I$5:$I$16,TRUE) | C9: 0であること
A10: 主要比較会社数 | B10: =COUNTIF('比較上の位置づけ'!$C$5:$C$16,"主要比較会社") | C10: 5〜8社を目安
A11: 候補社数 | B11: =COUNTA('比較上の位置づけ'!$A$5:$A$16) | C11: 12社であること
A12: 外部リンク | B12: なし | C12: 教育用ケースデータのみを使用
